travo/__init__.py
travo/_version.py
travo/assignment.py
travo/console_scripts.py
travo/course.py
travo/dashboards.py
travo/gitlab.py
travo/homework.py
travo/i18n.py
travo/jupyter_course.py
travo/nbgrader_utils.py
travo/py.typed
travo/script.py
travo/utils.py
travo/locale/travo.en.yml
travo/locale/travo.fr.yml
travo/tests/__init__.py
travo/tests/test_assignement.py
travo/tests/test_console_scripts.py
travo/tests/test_course.py
travo/tests/test_gitlab.py
travo/tests/test_jupyter_course.py
travo/tests/test_script.py
travo/tests/test_utils.py
travo-2.0.0.dist-info/METADATA
travo-2.0.0.dist-info/WHEEL
travo-2.0.0.dist-info/entry_points.txt
travo-2.0.0.dist-info/licenses/AUTHORS
travo-2.0.0.dist-info/licenses/LICENSE
travo-2.0.0.dist-info/RECORD
