Metadata-Version: 2.4
Name: travo
Version: 2.0.0
Summary: Management tools for gitlab-based assignment workflows
Project-URL: homepage, https://travo-cr.gitlab.io/travo/
Project-URL: documentation, https://travo-cr.gitlab.io/travo/
Project-URL: repository, https://gitlab.com/travo-cr/travo.git/
Project-URL: changelog, https://travo-cr.gitlab.io/travo/changelog.html
Author: Pierre Thomas Froidevaux, Alexandre Blondin-Massé, Jean Privat, Nicolas M. Thiéry, Chiara Marmo, Jérémy Neveu
Maintainer-email: "Nicolas M. Thiéry" <Nicolas.Thiery@universite-paris-saclay.fr>, Chiara Marmo <chiara.marmo@universite-paris-saclay.fr>
License: CC
License-File: AUTHORS
License-File: LICENSE
Classifier: Development Status :: 3 - Alpha
Classifier: Intended Audience :: Information Technology
Classifier: Programming Language :: Python :: 3
Classifier: Topic :: Scientific/Engineering
Requires-Python: >=3.10
Requires-Dist: anybadge
Requires-Dist: colorlog
Requires-Dist: deprecation
Requires-Dist: i18nice[yaml]
Requires-Dist: pytest
Requires-Dist: requests
Requires-Dist: tqdm
Requires-Dist: typing-utils
Provides-Extra: all
Requires-Dist: docutils<0.22; extra == 'all'
Requires-Dist: ipydatagrid; extra == 'all'
Requires-Dist: ipykernel; extra == 'all'
Requires-Dist: ipylab; extra == 'all'
Requires-Dist: ipywidgets; extra == 'all'
Requires-Dist: jupytext>=1.11.2; extra == 'all'
Requires-Dist: mypy; extra == 'all'
Requires-Dist: myst-nb; extra == 'all'
Requires-Dist: myst-parser>=0.13.1; extra == 'all'
Requires-Dist: nbconvert; extra == 'all'
Requires-Dist: nbgrader; extra == 'all'
Requires-Dist: numpy; extra == 'all'
Requires-Dist: numpydoc; extra == 'all'
Requires-Dist: pandas; extra == 'all'
Requires-Dist: pytest; extra == 'all'
Requires-Dist: python-gitlab; extra == 'all'
Requires-Dist: sphinx; extra == 'all'
Requires-Dist: sphinx-autoapi; extra == 'all'
Requires-Dist: sphinx-copybutton>0.2.9; extra == 'all'
Requires-Dist: sphinx-rtd-theme; extra == 'all'
Requires-Dist: sphinx-tabs; extra == 'all'
Requires-Dist: sphinx-togglebutton; extra == 'all'
Requires-Dist: tox-docker; extra == 'all'
Requires-Dist: types-requests; extra == 'all'
Requires-Dist: types-setuptools; extra == 'all'
Requires-Dist: types-toml; extra == 'all'
Provides-Extra: doc
Requires-Dist: docutils<0.22; extra == 'doc'
Requires-Dist: ipykernel; extra == 'doc'
Requires-Dist: jupytext>=1.11.2; extra == 'doc'
Requires-Dist: myst-nb; extra == 'doc'
Requires-Dist: myst-parser>=0.13.1; extra == 'doc'
Requires-Dist: nbconvert; extra == 'doc'
Requires-Dist: numpy; extra == 'doc'
Requires-Dist: numpydoc; extra == 'doc'
Requires-Dist: pandas; extra == 'doc'
Requires-Dist: pytest; extra == 'doc'
Requires-Dist: sphinx; extra == 'doc'
Requires-Dist: sphinx-autoapi; extra == 'doc'
Requires-Dist: sphinx-copybutton>0.2.9; extra == 'doc'
Requires-Dist: sphinx-rtd-theme; extra == 'doc'
Requires-Dist: sphinx-tabs; extra == 'doc'
Requires-Dist: sphinx-togglebutton; extra == 'doc'
Provides-Extra: jupyter
Requires-Dist: ipydatagrid; extra == 'jupyter'
Requires-Dist: ipylab; extra == 'jupyter'
Requires-Dist: ipywidgets; extra == 'jupyter'
Requires-Dist: jupytext>=1.11.2; extra == 'jupyter'
Requires-Dist: nbgrader; extra == 'jupyter'
Requires-Dist: numpy; extra == 'jupyter'
Requires-Dist: pandas; extra == 'jupyter'
Provides-Extra: test
Requires-Dist: ipydatagrid; extra == 'test'
Requires-Dist: mypy; extra == 'test'
Requires-Dist: nbgrader; extra == 'test'
Requires-Dist: pytest; extra == 'test'
Requires-Dist: python-gitlab; extra == 'test'
Requires-Dist: tox-docker; extra == 'test'
Requires-Dist: types-requests; extra == 'test'
Requires-Dist: types-setuptools; extra == 'test'
Requires-Dist: types-toml; extra == 'test'
